{"frames": {

"player-0":
{
	"frame": {"x":60,"y":0,"w":24,"h":30},
	"rotated": false,
	"trimmed": false,
	"spriteSourceSize": {"x":12,"y":18,"w":24,"h":30},
	"sourceSize": {"w":24,"h":30},
	"pivot": {"x":0.5,"y":0.533333}
},
"player-1":
{
	"frame": {"x":84,"y":0,"w":24,"h":30},
	"rotated": false,
	"trimmed": false,
	"spriteSourceSize": {"x":12,"y":18,"w":24,"h":30},
	"sourceSize": {"w":24,"h":30},
	"pivot": {"x":0.5,"y":0.533333}
},
"player-2":
{
	"frame": {"x":108,"y":0,"w":24,"h":30},
	"rotated": false,
	"trimmed": false,
	"spriteSourceSize": {"x":12,"y":18,"w":24,"h":30},
	"sourceSize": {"w":24,"h":30},
	"pivot": {"x":0.5,"y":0.533333}
},
"player-3":
{
	"frame": {"x":132,"y":0,"w":24,"h":30},
	"rotated": false,
	"trimmed": false,
	"spriteSourceSize": {"x":12,"y":18,"w":24,"h":30},
	"sourceSize": {"w":24,"h":30},
	"pivot": {"x":0.5,"y":0.533333}
},
"player-4":
{
	"frame": {"x":156,"y":0,"w":24,"h":30},
	"rotated": false,
	"trimmed": false,
	"spriteSourceSize": {"x":12,"y":18,"w":24,"h":30},
	"sourceSize": {"w":24,"h":30},
	"pivot": {"x":0.5,"y":0.533333}
},
"player-5":
{
	"frame": {"x":180,"y":0,"w":24,"h":30},
	"rotated": false,
	"trimmed": false,
	"spriteSourceSize": {"x":12,"y":18,"w":24,"h":30},
	"sourceSize": {"w":24,"h":30},
	"pivot": {"x":0.5,"y":0.533333}
},
"player-6":
{
	"frame": {"x":204,"y":0,"w":24,"h":30},
	"rotated": false,
	"trimmed": false,
	"spriteSourceSize": {"x":12,"y":18,"w":24,"h":30},
	"sourceSize": {"w":24,"h":30},
	"pivot": {"x":0.5,"y":0.533333}
},
"player-7":
{
	"frame": {"x":228,"y":0,"w":24,"h":30},
	"rotated": false,
	"trimmed": false,
	"spriteSourceSize": {"x":12,"y":18,"w":24,"h":30},
	"sourceSize": {"w":24,"h":30},
	"pivot": {"x":0.5,"y":0.533333}
},
"player-8":
{
	"frame": {"x":252,"y":0,"w":24,"h":30},
	"rotated": false,
	"trimmed": false,
	"spriteSourceSize": {"x":12,"y":18,"w":24,"h":30},
	"sourceSize": {"w":24,"h":30},
	"pivot": {"x":0.5,"y":0.533333}
},
"player-9":
{
	"frame": {"x":276,"y":0,"w":24,"h":30},
	"rotated": false,
	"trimmed": false,
	"spriteSourceSize": {"x":12,"y":18,"w":24,"h":30},
	"sourceSize": {"w":24,"h":30},
	"pivot": {"x":0.5,"y":0.533333}
},
"player-10":
{
	"frame": {"x":300,"y":0,"w":24,"h":30},
	"rotated": false,
	"trimmed": false,
	"spriteSourceSize": {"x":12,"y":18,"w":24,"h":30},
	"sourceSize": {"w":24,"h":30},
	"pivot": {"x":0.5,"y":0.533333}
},
"player-11":
{
	"frame": {"x":324,"y":0,"w":24,"h":30},
	"rotated": false,
	"trimmed": false,
	"spriteSourceSize": {"x":12,"y":18,"w":24,"h":30},
	"sourceSize": {"w":24,"h":30},
	"pivot": {"x":0.5,"y":0.533333}
},
"player-12":
{
	"frame": {"x":348,"y":0,"w":24,"h":30},
	"rotated": false,
	"trimmed": false,
	"spriteSourceSize": {"x":12,"y":18,"w":24,"h":30},
	"sourceSize": {"w":24,"h":30},
	"pivot": {"x":0.5,"y":0.533333}
},
"player-13":
{
	"frame": {"x":372,"y":0,"w":24,"h":30},
	"rotated": false,
	"trimmed": false,
	"spriteSourceSize": {"x":12,"y":18,"w":24,"h":30},
	"sourceSize": {"w":24,"h":30},
	"pivot": {"x":0.5,"y":0.533333}
},
"player-14":
{
	"frame": {"x":396,"y":0,"w":24,"h":30},
	"rotated": false,
	"trimmed": false,
	"spriteSourceSize": {"x":12,"y":18,"w":24,"h":30},
	"sourceSize": {"w":24,"h":30},
	"pivot": {"x":0.5,"y":0.533333}
},
"player-15":
{
	"frame": {"x":420,"y":0,"w":24,"h":30},
	"rotated": false,
	"trimmed": false,
	"spriteSourceSize": {"x":12,"y":18,"w":24,"h":30},
	"sourceSize": {"w":24,"h":30},
	"pivot": {"x":0.5,"y":0.533333}
},
"player-16":
{
	"frame": {"x":444,"y":0,"w":24,"h":30},
	"rotated": false,
	"trimmed": false,
	"spriteSourceSize": {"x":12,"y":18,"w":24,"h":30},
	"sourceSize": {"w":24,"h":30},
	"pivot": {"x":0.5,"y":0.533333}
},
"player-17":
{
	"frame": {"x":468,"y":0,"w":24,"h":30},
	"rotated": false,
	"trimmed": false,
	"spriteSourceSize": {"x":12,"y":18,"w":24,"h":30},
	"sourceSize": {"w":24,"h":30},
	"pivot": {"x":0.5,"y":0.533333}
},
"player-18":
{
	"frame": {"x":0,"y":30,"w":24,"h":30},
	"rotated": false,
	"trimmed": false,
	"spriteSourceSize": {"x":12,"y":18,"w":24,"h":30},
	"sourceSize": {"w":24,"h":30},
	"pivot": {"x":0.5,"y":0.533333}
},
"player-19":
{
	"frame": {"x":24,"y":30,"w":24,"h":30},
	"rotated": false,
	"trimmed": false,
	"spriteSourceSize": {"x":12,"y":18,"w":24,"h":30},
	"sourceSize": {"w":24,"h":30},
	"pivot": {"x":0.5,"y":0.533333}
},
"player-20":
{
	"frame": {"x":48,"y":30,"w":24,"h":30},
	"rotated": false,
	"trimmed": false,
	"spriteSourceSize": {"x":12,"y":18,"w":24,"h":30},
	"sourceSize": {"w":24,"h":30},
	"pivot": {"x":0.5,"y":0.533333}
},
"player-21":
{
	"frame": {"x":72,"y":30,"w":24,"h":30},
	"rotated": false,
	"trimmed": false,
	"spriteSourceSize": {"x":12,"y":18,"w":24,"h":30},
	"sourceSize": {"w":24,"h":30},
	"pivot": {"x":0.5,"y":0.533333}
},
"player-22":
{
	"frame": {"x":96,"y":30,"w":24,"h":30},
	"rotated": false,
	"trimmed": false,
	"spriteSourceSize": {"x":12,"y":18,"w":24,"h":30},
	"sourceSize": {"w":24,"h":30},
	"pivot": {"x":0.5,"y":0.533333}
},
"player-23":
{
	"frame": {"x":120,"y":30,"w":24,"h":30},
	"rotated": false,
	"trimmed": false,
	"spriteSourceSize": {"x":12,"y":18,"w":24,"h":30},
	"sourceSize": {"w":24,"h":30},
	"pivot": {"x":0.5,"y":0.533333}
},
"player-24":
{
	"frame": {"x":144,"y":30,"w":24,"h":30},
	"rotated": false,
	"trimmed": false,
	"spriteSourceSize": {"x":12,"y":18,"w":24,"h":30},
	"sourceSize": {"w":24,"h":30},
	"pivot": {"x":0.5,"y":0.533333}
},
"player-25":
{
	"frame": {"x":168,"y":30,"w":24,"h":30},
	"rotated": false,
	"trimmed": false,
	"spriteSourceSize": {"x":12,"y":18,"w":24,"h":30},
	"sourceSize": {"w":24,"h":30},
	"pivot": {"x":0.5,"y":0.533333}
},
"player-26":
{
	"frame": {"x":192,"y":30,"w":24,"h":30},
	"rotated": false,
	"trimmed": false,
	"spriteSourceSize": {"x":12,"y":18,"w":24,"h":30},
	"sourceSize": {"w":24,"h":30},
	"pivot": {"x":0.5,"y":0.533333}
},
"player-27":
{
	"frame": {"x":216,"y":30,"w":24,"h":30},
	"rotated": false,
	"trimmed": false,
	"spriteSourceSize": {"x":12,"y":18,"w":24,"h":30},
	"sourceSize": {"w":24,"h":30},
	"pivot": {"x":0.5,"y":0.533333}
},
"player-28":
{
	"frame": {"x":240,"y":30,"w":24,"h":30},
	"rotated": false,
	"trimmed": false,
	"spriteSourceSize": {"x":12,"y":18,"w":24,"h":30},
	"sourceSize": {"w":24,"h":30},
	"pivot": {"x":0.5,"y":0.533333}
},
"player-29":
{
	"frame": {"x":264,"y":30,"w":24,"h":30},
	"rotated": false,
	"trimmed": false,
	"spriteSourceSize": {"x":12,"y":18,"w":24,"h":30},
	"sourceSize": {"w":24,"h":30},
	"pivot": {"x":0.5,"y":0.533333}
},
"player-30":
{
	"frame": {"x":288,"y":30,"w":24,"h":30},
	"rotated": false,
	"trimmed": false,
	"spriteSourceSize": {"x":12,"y":18,"w":24,"h":30},
	"sourceSize": {"w":24,"h":30},
	"pivot": {"x":0.5,"y":0.533333}
},
"player-31":
{
	"frame": {"x":312,"y":30,"w":24,"h":30},
	"rotated": false,
	"trimmed": false,
	"spriteSourceSize": {"x":12,"y":18,"w":24,"h":30},
	"sourceSize": {"w":24,"h":30},
	"pivot": {"x":0.5,"y":0.533333}
},
"player-32":
{
	"frame": {"x":336,"y":30,"w":24,"h":30},
	"rotated": false,
	"trimmed": false,
	"spriteSourceSize": {"x":12,"y":18,"w":24,"h":30},
	"sourceSize": {"w":24,"h":30},
	"pivot": {"x":0.5,"y":0.533333}
},
"player-33":
{
	"frame": {"x":360,"y":30,"w":24,"h":30},
	"rotated": false,
	"trimmed": false,
	"spriteSourceSize": {"x":12,"y":18,"w":24,"h":30},
	"sourceSize": {"w":24,"h":30},
	"pivot": {"x":0.5,"y":0.533333}
},
"player-34":
{
	"frame": {"x":384,"y":30,"w":24,"h":30},
	"rotated": false,
	"trimmed": false,
	"spriteSourceSize": {"x":12,"y":18,"w":24,"h":30},
	"sourceSize": {"w":24,"h":30},
	"pivot": {"x":0.5,"y":0.533333}
},
"player-35":
{
	"frame": {"x":408,"y":30,"w":24,"h":30},
	"rotated": false,
	"trimmed": false,
	"spriteSourceSize": {"x":12,"y":18,"w":24,"h":30},
	"sourceSize": {"w":24,"h":30},
	"pivot": {"x":0.5,"y":0.533333}
},
"player-36":
{
	"frame": {"x":432,"y":30,"w":24,"h":30},
	"rotated": false,
	"trimmed": false,
	"spriteSourceSize": {"x":12,"y":18,"w":24,"h":30},
	"sourceSize": {"w":24,"h":30},
	"pivot": {"x":0.5,"y":0.533333}
},
"player-37":
{
	"frame": {"x":456,"y":30,"w":30,"h":30},
	"rotated": false,
	"trimmed": false,
	"spriteSourceSize": {"x":12,"y":18,"w":30,"h":30},
	"sourceSize": {"w":30,"h":30},
	"pivot": {"x":0.4,"y":0.533333}
},
"player-38":
{
	"frame": {"x":0,"y":60,"w":30,"h":30},
	"rotated": false,
	"trimmed": false,
	"spriteSourceSize": {"x":12,"y":18,"w":30,"h":30},
	"sourceSize": {"w":30,"h":30},
	"pivot": {"x":0.4,"y":0.533333}
},
"player-39":
{
	"frame": {"x":30,"y":60,"w":24,"h":30},
	"rotated": false,
	"trimmed": false,
	"spriteSourceSize": {"x":12,"y":18,"w":24,"h":30},
	"sourceSize": {"w":24,"h":30},
	"pivot": {"x":0.5,"y":0.533333}
},
"player-40":
{
	"frame": {"x":54,"y":60,"w":30,"h":30},
	"rotated": false,
	"trimmed": false,
	"spriteSourceSize": {"x":12,"y":18,"w":30,"h":30},
	"sourceSize": {"w":30,"h":30},
	"pivot": {"x":0.4,"y":0.533333}
},
"player-41":
{
	"frame": {"x":84,"y":60,"w":42,"h":30},
	"rotated": false,
	"trimmed": false,
	"spriteSourceSize": {"x":6,"y":18,"w":42,"h":30},
	"sourceSize": {"w":42,"h":30},
	"pivot": {"x":0.428571,"y":0.533333}
},
"player-42":
{
	"frame": {"x":126,"y":60,"w":30,"h":30},
	"rotated": false,
	"trimmed": false,
	"spriteSourceSize": {"x":6,"y":18,"w":30,"h":30},
	"sourceSize": {"w":30,"h":30},
	"pivot": {"x":0.6,"y":0.533333}
},
"player-43":
{
	"frame": {"x":156,"y":60,"w":24,"h":30},
	"rotated": false,
	"trimmed": false,
	"spriteSourceSize": {"x":12,"y":18,"w":24,"h":30},
	"sourceSize": {"w":24,"h":30},
	"pivot": {"x":0.5,"y":0.533333}
},
"player-44":
{
	"frame": {"x":180,"y":60,"w":30,"h":30},
	"rotated": false,
	"trimmed": false,
	"spriteSourceSize": {"x":12,"y":18,"w":30,"h":30},
	"sourceSize": {"w":30,"h":30},
	"pivot": {"x":0.4,"y":0.533333}
},
"player-45":
{
	"frame": {"x":210,"y":60,"w":30,"h":30},
	"rotated": false,
	"trimmed": false,
	"spriteSourceSize": {"x":6,"y":18,"w":30,"h":30},
	"sourceSize": {"w":30,"h":30},
	"pivot": {"x":0.6,"y":0.533333}
},
"player-46":
{
	"frame": {"x":240,"y":60,"w":30,"h":30},
	"rotated": false,
	"trimmed": false,
	"spriteSourceSize": {"x":6,"y":18,"w":30,"h":30},
	"sourceSize": {"w":30,"h":30},
	"pivot": {"x":0.6,"y":0.533333}
},
"player-47":
{
	"frame": {"x":270,"y":60,"w":24,"h":30},
	"rotated": false,
	"trimmed": false,
	"spriteSourceSize": {"x":12,"y":18,"w":24,"h":30},
	"sourceSize": {"w":24,"h":30},
	"pivot": {"x":0.5,"y":0.533333}
},
"player-48":
{
	"frame": {"x":294,"y":60,"w":24,"h":30},
	"rotated": false,
	"trimmed": false,
	"spriteSourceSize": {"x":12,"y":18,"w":24,"h":30},
	"sourceSize": {"w":24,"h":30},
	"pivot": {"x":0.5,"y":0.533333}
},
"player-49":
{
	"frame": {"x":0,"y":0,"w":30,"h":24},
	"rotated": false,
	"trimmed": false,
	"spriteSourceSize": {"x":12,"y":24,"w":30,"h":24},
	"sourceSize": {"w":30,"h":24},
	"pivot": {"x":0.4,"y":0.416666}
},
"player-50":
{
	"frame": {"x":30,"y":0,"w":30,"h":24},
	"rotated": false,
	"trimmed": false,
	"spriteSourceSize": {"x":12,"y":24,"w":30,"h":24},
	"sourceSize": {"w":30,"h":24},
	"pivot": {"x":0.4,"y":0.416666}
}},
"meta": {
	"app": "https://www.codeandweb.com/texturepacker",
	"version": "1.0",
	"image": "./assets/images/player.png",
	"format": "RGBA8888",
	"size": {"w":512,"h":512},
	"scale": "1",
	"smartupdate": "$TexturePacker:SmartUpdate:ca24c3f29cb6d3f959afcb1a74d0dc59:019a9d8d3fc739253338cc4c22b1aee0:86d5339b780aedd87b35e2b7c0a7e11b$"
}
}
